<?xml version="1.0" encoding="utf-8"?>
<resources>
  <color name="primary">#054678</color>
  <color name="primaryDark">#062E4C</color>
  <color name="accent">#FFC107</color>
  <color name="accentForMaterialEntry">#30BB6D</color>
  <color name="window_background">#FFFFFF</color>
  <color name="GreenIndicator">#51D929</color>
  <color name="BlueBarBackground">#054678</color>
  <color name="MetalBlueEntryHighLight">#929DF5</color>
  <color name="BlackCursor">#38463E</color>
  <color name="KindOfBlueHintColor">#37429B</color>
  <color name="SomethingLikeGreenForUnderLine">#30BB6D</color>
  <color name="NativeCellAndroidBackground">#FFFFFF</color>
  <color name="NativeCellAndroidTextColor">#054678</color>
</resources>